LICENSE
MANIFEST.in
README.rst
setup.py
version.txt
docs/HISTORY.txt
docs/LICENSE.GPL
docs/LICENSE.txt
plone/__init__.py
plone.profileview.egg-info/PKG-INFO
plone.profileview.egg-info/SOURCES.txt
plone.profileview.egg-info/dependency_links.txt
plone.profileview.egg-info/entry_points.txt
plone.profileview.egg-info/namespace_packages.txt
plone.profileview.egg-info/not-zip-safe
plone.profileview.egg-info/requires.txt
plone.profileview.egg-info/top_level.txt
plone/profileview/__init__.py
plone/profileview/configure.zcml
plone/profileview/browser/__init__.py
plone/profileview/browser/configure.zcml
plone/profileview/browser/profileview.py
plone/profileview/browser/resources/profileview.js
plone/profileview/browser/resources/angular/angular-resource.min.js
plone/profileview/browser/resources/angular/angular-resource.min.js.map
plone/profileview/browser/resources/angular/angular-route.min.js
plone/profileview/browser/resources/angular/angular-route.min.js.map
plone/profileview/browser/resources/angular/angular.min.js
plone/profileview/browser/resources/angular/angular.min.js.map
plone/profileview/browser/templates/ajax.pt