Metadata-Version: 1.1
Name: plone.profileview
Version: 0.2
Summary: BrowserView profiler
Home-page: http://github.com/eaudeweb/plone.profileview
Author: David Batranu
Author-email: dbatranu@gmail.com
License: GPL
Keywords: Plone BrowserView Profiler
Platform: UNKNOWN
Classifier: Framework :: Zope2
Classifier: Framework :: Zope3
Classifier: Framework :: Plone
Classifier: Framework :: Plone :: 4.3
Classifier: Framework :: Plone :: 5.0
Classifier: Programming Language :: Zope
Classifier: Programming Language :: Python
Classifier: Topic :: Software Development :: Libraries :: Python Modules
Classifier: License :: OSI Approved :: GNU General Public License (GPL)
Classifier: License :: OSI Approved :: Mozilla Public License 1.0 (MPL)
